LICENSE
README.md
setup.py
NlpToolkit_WordNet.egg-info/PKG-INFO
NlpToolkit_WordNet.egg-info/SOURCES.txt
NlpToolkit_WordNet.egg-info/dependency_links.txt
NlpToolkit_WordNet.egg-info/requires.txt
NlpToolkit_WordNet.egg-info/top_level.txt
WordNet/CategoryType.py
WordNet/IdMapping.py
WordNet/InterlingualDependencyType.py
WordNet/InterlingualRelation.py
WordNet/Literal.py
WordNet/Relation.py
WordNet/SemanticRelation.py
WordNet/SemanticRelationType.py
WordNet/SynSet.py
WordNet/Synonym.py
WordNet/WordNet.py
WordNet/__init__.py
WordNet/Similarity/ICSimilarity.py
WordNet/Similarity/JCN.py
WordNet/Similarity/LCH.py
WordNet/Similarity/Lin.py
WordNet/Similarity/Resnik.py
WordNet/Similarity/Similarity.py
WordNet/Similarity/SimilarityPath.py
WordNet/Similarity/WuPalmer.py
WordNet/Similarity/__init__.py
WordNet/data/__init__.py
WordNet/data/english_exception.xml
WordNet/data/english_wordnet_version_31.xml
WordNet/data/turkish_wordnet.xml