Metadata-Version: 2.1
Name: NlpToolkit-WordNet
Version: 1.0.23
Summary: Turkish WordNet KeNet
Home-page: https://github.com/StarlangSoftware/TurkishWordNet-Py
Author: olcaytaner
Author-email: olcay.yildiz@ozyegin.edu.tr
License: UNKNOWN
Platform: UNKNOWN
License-File: LICENSE
